datapizza/modules/parsers/docling/__init__.py
datapizza/modules/parsers/docling/docling_parser.py
datapizza/modules/parsers/docling/ocr_options.py
datapizza/modules/parsers/docling/utils.py
datapizza/modules/parsers/docling/tests/conftest.py
datapizza/modules/parsers/docling/tests/test_docling_parser.py
datapizza_ai_parsers_docling-0.0.8.dist-info/METADATA
datapizza_ai_parsers_docling-0.0.8.dist-info/WHEEL
datapizza_ai_parsers_docling-0.0.8.dist-info/RECORD
