Metadata-Version: 2.4
Name: datapizza-ai-parsers-docling
Version: 0.0.8
Summary: Doclign parser for the datapizza-ai framework
Author-email: Datapizza <datapizza@datapizza.tech>
License: MIT
Classifier: License :: OSI Approved :: MIT License
Classifier: Operating System :: OS Independent
Classifier: Programming Language :: Python :: 3
Requires-Python: <4,>=3.10.0
Requires-Dist: datapizza-ai-core<0.1.0,>=0.0.1
Requires-Dist: docling>=2.53.0
Requires-Dist: easyocr>=1.7.0
